esw/__init__.py
py_esw-0.1.6.dist-info/METADATA
py_esw-0.1.6.dist-info/WHEEL
py_esw-0.1.6.dist-info/top_level.txt
py_esw-0.1.6.dist-info/RECORD
