Metadata-Version: 2.1
Name: py-esw
Version: 0.1.6
Summary: UNKNOWN
License: UNKNOWN
Platform: UNKNOWN
Requires-Dist: requests (>=2.26.0)
